pixivpy3/__init__.py
pixivpy3/aapi.py
pixivpy3/api.py
pixivpy3/bapi.py
pixivpy3/py.typed
pixivpy3/utils.py
pixivpy3-3.7.4.dist-info/LICENSE
pixivpy3-3.7.4.dist-info/METADATA
pixivpy3-3.7.4.dist-info/WHEEL
pixivpy3-3.7.4.dist-info/RECORD
