Metadata-Version: 2.1
Name: pixivpy3
Version: 3.7.4
Summary: Pixiv API for Python (with 6.x AppAPI supported)
Home-page: https://github.com/upbit/pixivpy
License: Unlicense
Keywords: pixiv,api,pixivapi
Author: upbit
Author-email: rmusique@gmail.com
Requires-Python: >=3.7,<4.0
Classifier: License :: OSI Approved
Classifier: Operating System :: OS Independent
Classifier: Programming Language :: Python :: 3
Classifier: Programming Language :: Python :: 3.7
Classifier: Programming Language :: Python :: 3.8
Classifier: Programming Language :: Python :: 3.9
Classifier: Programming Language :: Python :: 3.10
Classifier: Programming Language :: Python :: 3.11
Classifier: Programming Language :: Python :: 3 :: Only
Requires-Dist: cloudscraper (>=1.2.58,<2.0.0)
Requires-Dist: requests (>=2.31.0,<3.0.0)
Requires-Dist: requests-toolbelt (>=1.0.0,<2.0.0)
Requires-Dist: typing-extensions (>=4.1.1,<5.0.0)
Requires-Dist: urllib3 (>=2.0.7,<3.0.0)
